day-2/rtl/latch.sv
module latch (
    input logic d, 
    input logic clk,
    input logic reset ,
    output logic q
);
    always_ff @( posedge clk or posedge reset ) begin 
        if (!reset) begin
            q <= d; 
        end else begin
            q <= 0;
        end
        
    end
endmodule

day-2/tb/latch_tb.sv
module latch_tb;
logic d ;
logic clk ;
logic r ;
logic q ;

latch dut(
    .d(d),
    .clk(clk),
    .reset(r),
    .q(q)
);
always #5 clk = ~clk ;
initial begin
    clk =0;
    r=1;
    d=0;
    #10;
    r=0;
        d = 1 ;
    #10 d = 0 ;
    #10 d = 1 ;
    #10 d = 0 ;
    #10 d = 1 ;
    #10 $finish;

end

initial begin
    $dumpfile("latch.vcd");
    $dumpvars(0,latch_tb);

end

initial begin
    $monitor("time=%0t | reset=%b |clk=%b| d=%b | q=%b |",$time,r,clk,d,q);
end
    
endmodule

day-2/latch.vcd
$date
	Wed Jun 10 23:54:44 2026
$end
$version
	Icarus Verilog
$end
$timescale
	1s
$end
$scope module latch_tb $end
$var wire 1 ! q $end
$var reg 1 " clk $end
$var reg 1 # d $end
$var reg 1 $ r $end
$scope module dut $end
$var wire 1 " clk $end
$var wire 1 # d $end
$var wire 1 $ reset $end
$var reg 1 ! q $end
$upscope $end
$upscope $end
$enddefinitions $end
$comment Show the parameter values. $end
$dumpall
$end
#0
$dumpvars
1$
0#
0"
0!
$end
#5
1"
#10
0"
1#
0$
#15
1!
1"
#20
0"
0#
#25
0!
1"
#30
0"
1#
#35
1!
1"
#40
0"
0#
#45
0!
1"
#50
0"
1#
#55
1!
1"
