day-5/rtl/foreach.sv
/*
Task 1

Create:

Logic [7:0] arr[5];

Store:

10
20
30
40
50

Print using foreach.

Task 2

Initialize an array using:

Foreach(arr[i])

Store:

0
1
2
3
4

Print all values.



Task 3

Create:

Logic [7:0] mem[4];

Store:

AA
BB
CC
DD

Print using both:

For

Foreach

*/

module for_each (
    input logic [7:0]arr_1[5],
    input logic [7:0]arr_2[5],
    input logic [7:0]arr_3[5]
);
    
endmodule

day-5/tb/foreach_tb.sv
module for_each_tb;
logic [7:0]arr_1[5];
logic [7:0]arr_2[5];
logic [7:0]arr_3[5];

integer i;
    for_each dut(
        .arr_1(arr_1),
        .arr_2(arr_2),
        .arr_3(arr_3)

    );
    initial begin
        $dumpfile("foreach.vcd");
        $dumpvars(0,for_each_tb);
        //task-1

         foreach(arr_1[i])
    begin
        arr_1[i] =(( i + 1) * 10);
        
    end
    //task-2

    foreach(arr_2[i])
    begin
        arr_2[i] = i;
    end
    //task-3

    foreach(arr_3[i])
    begin
        arr_3[i] = (i+10);
        #10;
        arr_3[i] = ((arr_3[i]*(16**1))+(arr_3[i]*(16**0)));
        
    end
    

    foreach(arr_1[i])
    begin
        

        $display("arr[%0d] = %0d",i,arr_1[i]);

    end

     foreach(arr_2[i])
    begin
        

        $display("arr[%0d] = %0d",i,arr_2[i]);

    end
    //task-3

    for (i =0 ;i<5 ;i++ ) begin
        arr_3[i] = (i+10);
        #10;
        arr_3[i] = ((arr_3[i]*(16**1))+(arr_3[i]*(16**0)));
        $display("arr[%0d] = %0h",i,arr_3[i]);
        
    end

     foreach(arr_3[i])
    begin
        

        $display("arr[%0d] = %0h",i,arr_3[i]);

    end


        


    end

   
endmodule

day-5/foreach.vcd
$date
	Sat Jun 13 16:39:19 2026
$end
$version
	Icarus Verilog
$end
$timescale
	1s
$end
$scope module for_each_tb $end
$var integer 32 ! i [31:0] $end
$scope module dut $end
$upscope $end
$scope begin $ivl_foreach0 $end
$var integer 32 " i [31:0] $end
$upscope $end
$scope begin $ivl_foreach1 $end
$var integer 32 # i [31:0] $end
$upscope $end
$scope begin $ivl_foreach2 $end
$var integer 32 $ i [31:0] $end
$upscope $end
$scope begin $ivl_foreach3 $end
$var integer 32 % i [31:0] $end
$upscope $end
$scope begin $ivl_foreach4 $end
$var integer 32 & i [31:0] $end
$upscope $end
$scope begin $ivl_foreach5 $end
$var integer 32 ' i [31:0] $end
$upscope $end
$upscope $end
$enddefinitions $end
$comment Show the parameter values. $end
$dumpall
$end
#0
$dumpvars
b0 '
b0 &
b0 %
b0 $
b101 #
b101 "
bx !
$end
#10
b1 $
#20
b10 $
#30
b11 $
#40
b100 $
#50
b0 !
b101 &
b101 %
b101 $
#60
b1 !
#70
b10 !
#80
b11 !
#90
b100 !
#100
b101 '
b101 !
